duviz.py
duviz-3.2.0.dist-info/LICENSE.txt
duviz-3.2.0.dist-info/METADATA
duviz-3.2.0.dist-info/WHEEL
duviz-3.2.0.dist-info/entry_points.txt
duviz-3.2.0.dist-info/top_level.txt
duviz-3.2.0.dist-info/RECORD
